markdown_chunker/__init__.py
markdown_chunker/chunking_strategy.py
markdown_chunker/cli.py
markdown_chunker/content_handlers.py
markdown_chunker/utils.py
markdown_chunker-0.1.3.dist-info/LICENSE
markdown_chunker-0.1.3.dist-info/METADATA
markdown_chunker-0.1.3.dist-info/WHEEL
markdown_chunker-0.1.3.dist-info/entry_points.txt
markdown_chunker-0.1.3.dist-info/top_level.txt
markdown_chunker-0.1.3.dist-info/RECORD
